[
    {
        "model": "api.service",
        "pk": 1,
        "fields": {
            "name": "2k",
            "cname": "2K",
            "path": "/statut/2k",
            "countries": [
                74,
                230
            ]
        }
    },
    {
        "model": "api.service",
        "pk": 2,
        "fields": {
            "name": "Alaska Communication",
            "cname": "ALASKACOMMUNICATION",
            "path": "/statut/alaska-communication",
            "countries": [
                230
            ]
        }
    },
    {
        "model": "api.service",
        "pk": 3,
        "fields": {
            "name": "Allstate",
            "cname": "ALLSTATE",
            "path": "/statut/allstate",
            "countries": [
                230
            ]
        }
    },
    {
        "model": "api.service",
        "pk": 4,
        "fields": {
            "name": "Amazon",
            "cname": "AMAZON",
            "path": "/statut/amazon",
            "countries": [
                74,
                230
            ]
        }
    },
    {
        "model": "api.service",
        "pk": 5,
        "fields": {
            "name": "Amazon Prime",
            "cname": "AMAZONPRIME",
            "path": "/statut/amazon-prime-instant-video",
            "countries": [
                74,
                230
            ]
        }
    },
    {
        "model": "api.service",
        "pk": 6,
        "fields": {
            "name": "Amazon Web Services",
            "cname": "AWS",
            "path": "/statut/amazon-web-services-aws",
            "countries": [
                74,
                230
            ]
        }
    },
    {
        "model": "api.service",
        "pk": 7,
        "fields": {
            "name": "American Electric Power - Ohio",
            "cname": "AEPOHIO",
            "path": "/statut/american-electric-power-ohio",
            "countries": [
                230
            ]
        }
    },
    {
        "model": "api.service",
        "pk": 8,
        "fields": {
            "name": "American Electric Power - Texas",
            "cname": "AEPTEXAS",
            "path": "/statut/american-electric-power-texas",
            "countries": [
                74,
                230
            ]
        }
    },
    {
        "model": "api.service",
        "pk": 9,
        "fields": {
            "name": "Anthem",
            "cname": "ANTHEM",
            "path": "/statut/anthem-game",
            "countries": [
                74,
                230
            ]
        }
    },
    {
        "model": "api.service",
        "pk": 10,
        "fields": {
            "name": "AOL",
            "cname": "AOL",
            "path": "/statut/aol-america-online",
            "countries": [
                230
            ]
        }
    },
    {
        "model": "api.service",
        "pk": 11,
        "fields": {
            "name": "Apex Legends",
            "cname": "APEXLEGENDS",
            "path": "/statut/apex-legends",
            "countries": [
                74,
                230
            ]
        }
    },
    {
        "model": "api.service",
        "pk": 12,
        "fields": {
            "name": "Appalachian Power",
            "cname": "APPALACHIANPOWER",
            "path": "/statut/appalachian-power",
            "countries": [
                230
            ]
        }
    },
    {
        "model": "api.service",
        "pk": 13,
        "fields": {
            "name": "Apple Store",
            "cname": "APPLESTORE",
            "path": "/statut/apple-store",
            "countries": [
                74,
                230
            ]
        }
    },
    {
        "model": "api.service",
        "pk": 14,
        "fields": {
            "name": "Arlo",
            "cname": "ARLO",
            "path": "/statut/arlo",
            "countries": [
                74,
                230
            ]
        }
    },
    {
        "model": "api.service",
        "pk": 15,
        "fields": {
            "name": "Arvig",
            "cname": "ARVIG",
            "path": "/statut/arvig",
            "countries": [
                230
            ]
        }
    },
    {
        "model": "api.service",
        "pk": 16,
        "fields": {
            "name": "Atlantic Broadband",
            "cname": "ATLANTICBROADBAND",
            "path": "/statut/atlantic-broadband",
            "countries": [
                230
            ]
        }
    },
    {
        "model": "api.service",
        "pk": 17,
        "fields": {
            "name": "AT&T",
            "cname": "ATT",
            "path": "/statut/att",
            "countries": [
                230
            ]
        }
    },
    {
        "model": "api.service",
        "pk": 18,
        "fields": {
            "name": "Bank Of America",
            "cname": "BANKOFAMERICA",
            "path": "/statut/bank-of-america",
            "countries": [
                230
            ]
        }
    },
    {
        "model": "api.service",
        "pk": 19,
        "fields": {
            "name": "Battlefield 2042",
            "cname": "BATTLEFIELD",
            "path": "/statut/battlefield-one",
            "countries": [
                74,
                230
            ]
        }
    },
    {
        "model": "api.service",
        "pk": 20,
        "fields": {
            "name": "Battle Net",
            "cname": "BATTLENET",
            "path": "/statut/battlenet-blizzard-entertainment",
            "countries": [
                74,
                230
            ]
        }
    },
    {
        "model": "api.service",
        "pk": 21,
        "fields": {
            "name": "Binance",
            "cname": "BINANCE",
            "path": "/statut/binance",
            "countries": [
                74,
                230
            ]
        }
    },
    {
        "model": "api.service",
        "pk": 22,
        "fields": {
            "name": "Bitfinex",
            "cname": "BITFINEX",
            "path": "/statut/bitfinex",
            "countries": [
                74,
                230
            ]
        }
    },
    {
        "model": "api.service",
        "pk": 23,
        "fields": {
            "name": "Bitstamp",
            "cname": "BITSTAMP",
            "path": "/statut/bitstamp",
            "countries": [
                74,
                230
            ]
        }
    },
    {
        "model": "api.service",
        "pk": 24,
        "fields": {
            "name": "Boingo",
            "cname": "BOINGO",
            "path": "/statut/boingo",
            "countries": [
                230
            ]
        }
    },
    {
        "model": "api.service",
        "pk": 25,
        "fields": {
            "name": "Boost Mobile",
            "cname": "BOOSTMOBILE",
            "path": "/statut/boost-mobile",
            "countries": [
                230
            ]
        }
    },
    {
        "model": "api.service",
        "pk": 26,
        "fields": {
            "name": "Bouygues Telecom",
            "cname": "BOUYGUES",
            "path": "/statut/bouygues-telecom",
            "countries": [
                74
            ]
        }
    },
    {
        "model": "api.service",
        "pk": 27,
        "fields": {
            "name": "Buckeye Broadband",
            "cname": "BUCKEYEBROADBAND",
            "path": "/statut/buckeye-broadband",
            "countries": [
                230
            ]
        }
    },
    {
        "model": "api.service",
        "pk": 28,
        "fields": {
            "name": "C Spire Wireless",
            "cname": "CSPIRE",
            "path": "/statut/c-spire-wireless",
            "countries": [
                230
            ]
        }
    },
    {
        "model": "api.service",
        "pk": 29,
        "fields": {
            "name": "Cable One",
            "cname": "CABLEONE",
            "path": "/statut/cable-one",
            "countries": [
                230
            ]
        }
    },
    {
        "model": "api.service",
        "pk": 30,
        "fields": {
            "name": "Call Of Duty",
            "cname": "CALLOFDUTY",
            "path": "/statut/call-of-duty",
            "countries": [
                74,
                230
            ]
        }
    },
    {
        "model": "api.service",
        "pk": 31,
        "fields": {
            "name": "Canalsat",
            "cname": "CANALSAT",
            "path": "/statut/canalsat",
            "countries": [
                74,
                230
            ]
        }
    },
    {
        "model": "api.service",
        "pk": 32,
        "fields": {
            "name": "Candy Crush Saga",
            "cname": "CANDYCRUSH",
            "path": "/statut/candy-crush-saga",
            "countries": [
                74
            ]
        }
    },
    {
        "model": "api.service",
        "pk": 33,
        "fields": {
            "name": "Capital One",
            "cname": "CAPITALONE",
            "path": "/statut/capital-one",
            "countries": [
                230
            ]
        }
    },
    {
        "model": "api.service",
        "pk": 34,
        "fields": {
            "name": "CashApp",
            "cname": "CASHAPP",
            "path": "/statut/cashapp",
            "countries": [
                230
            ]
        }
    },
    {
        "model": "api.service",
        "pk": 35,
        "fields": {
            "name": "CenterPoint Energy",
            "cname": "CENTERPOINTENERGY",
            "path": "/statut/centerpoint-energy",
            "countries": [
                230
            ]
        }
    },
    {
        "model": "api.service",
        "pk": 36,
        "fields": {
            "name": "CenturyLink",
            "cname": "CENTURYLINK",
            "path": "/statut/centurylink",
            "countries": [
                230
            ]
        }
    },
    {
        "model": "api.service",
        "pk": 37,
        "fields": {
            "name": "Charter Communications",
            "cname": "CHARTERCOMMUNICATIONS",
            "path": "/statut/charter-communications",
            "countries": [
                230
            ]
        }
    },
    {
        "model": "api.service",
        "pk": 38,
        "fields": {
            "name": "Chase Bank",
            "cname": "CHASEBANK",
            "path": "/statut/chase-bank",
            "countries": [
                230
            ]
        }
    },
    {
        "model": "api.service",
        "pk": 39,
        "fields": {
            "name": "Cincinnati Bell",
            "cname": "CINCINNATIBELL",
            "path": "/statut/cincinnati-bell",
            "countries": [
                230
            ]
        }
    },
    {
        "model": "api.service",
        "pk": 40,
        "fields": {
            "name": "Citibank",
            "cname": "CITIBANK",
            "path": "/statut/citigroup-bank",
            "countries": [
                230
            ]
        }
    },
    {
        "model": "api.service",
        "pk": 41,
        "fields": {
            "name": "CloudfLare",
            "cname": "CLOUNDFLARE",
            "path": "/statut/cloundflare",
            "countries": [
                74,
                230
            ]
        }
    },
    {
        "model": "api.service",
        "pk": 42,
        "fields": {
            "name": "CMC Markets",
            "cname": "CMCMARKETS",
            "path": "/statut/cmc-markets",
            "countries": [
                74,
                230
            ]
        }
    },
    {
        "model": "api.service",
        "pk": 43,
        "fields": {
            "name": "Coinbase",
            "cname": "COINBASE",
            "path": "/statut/coinbase",
            "countries": [
                74,
                230
            ]
        }
    },
    {
        "model": "api.service",
        "pk": 44,
        "fields": {
            "name": "Comcast Xfinity",
            "cname": "COMCASTXFINITY",
            "path": "/statut/comcast-xfinity",
            "countries": [
                230
            ]
        }
    },
    {
        "model": "api.service",
        "pk": 45,
        "fields": {
            "name": "Consolidated Communications",
            "cname": "CONSOLIDATEDCOMMUNICATIONS",
            "path": "/statut/consolidated-communications",
            "countries": [
                230
            ]
        }
    },
    {
        "model": "api.service",
        "pk": 46,
        "fields": {
            "name": "Consolidated Edison",
            "cname": "CONSOLIDATEDEDISON",
            "path": "/statut/consolidated-edison",
            "countries": [
                230
            ]
        }
    },
    {
        "model": "api.service",
        "pk": 47,
        "fields": {
            "name": "Consumer Cellular",
            "cname": "CONSUMERCELLULAR",
            "path": "/statut/consumer-cellular",
            "countries": [
                230
            ]
        }
    },
    {
        "model": "api.service",
        "pk": 48,
        "fields": {
            "name": "Counter-Strike: Global Offensive",
            "cname": "CSGO",
            "path": "/statut/counter-strike-csgo",
            "countries": [
                74,
                230
            ]
        }
    },
    {
        "model": "api.service",
        "pk": 49,
        "fields": {
            "name": "Cok Communications",
            "cname": "COXCOMMUNICATIONS",
            "path": "/statut/cox-communications",
            "countries": [
                230
            ]
        }
    },
    {
        "model": "api.service",
        "pk": 50,
        "fields": {
            "name": "Craiglist",
            "cname": "CRAIGLIST",
            "path": "/statut/craiglist",
            "countries": [
                230
            ]
        }
    },
    {
        "model": "api.service",
        "pk": 51,
        "fields": {
            "name": "Cricket Wirless",
            "cname": "CRICKETWIRLESS",
            "path": "/statut/cricket-wireless",
            "countries": [
                230
            ]
        }
    },
    {
        "model": "api.service",
        "pk": 52,
        "fields": {
            "name": "Crunchyroll",
            "cname": "CRUNCHYROLL",
            "path": "/statut/crunchyroll",
            "countries": [
                74,
                230
            ]
        }
    },
    {
        "model": "api.service",
        "pk": 53,
        "fields": {
            "name": "Cryptopia",
            "cname": "CRYPTOPIA",
            "path": "/statut/cryptopia",
            "countries": [
                74,
                230
            ]
        }
    },
    {
        "model": "api.service",
        "pk": 54,
        "fields": {
            "name": "Cyberpunk 2077",
            "cname": "CYBERPUNK2077",
            "path": "/statut/cyberpunk-2077",
            "countries": [
                74,
                230
            ]
        }
    },
    {
        "model": "api.service",
        "pk": 55,
        "fields": {
            "name": "Destiny",
            "cname": "DESTINY",
            "path": "/statut/destiny",
            "countries": [
                74,
                230
            ]
        }
    },
    {
        "model": "api.service",
        "pk": 56,
        "fields": {
            "name": "DHL",
            "cname": "DHL",
            "path": "/statut/dhl-deutschland",
            "countries": [
                74
            ]
        }
    },
    {
        "model": "api.service",
        "pk": 57,
        "fields": {
            "name": "Diablo",
            "cname": "DIABLO",
            "path": "/statut/diablo",
            "countries": [
                74,
                230
            ]
        }
    },
    {
        "model": "api.service",
        "pk": 58,
        "fields": {
            "name": "Directv",
            "cname": "DIRECTV",
            "path": "/statut/directv",
            "countries": [
                230
            ]
        }
    },
    {
        "model": "api.service",
        "pk": 59,
        "fields": {
            "name": "Discord",
            "cname": "DISCORD",
            "path": "/statut/discord",
            "countries": [
                74,
                230
            ]
        }
    },
    {
        "model": "api.service",
        "pk": 60,
        "fields": {
            "name": "Dish Network",
            "cname": "DISHNETWORK",
            "path": "/statut/dish-network",
            "countries": [
                230
            ]
        }
    },
    {
        "model": "api.service",
        "pk": 61,
        "fields": {
            "name": "Disney Plus",
            "cname": "DISNEYPLUS",
            "path": "/statut/disney-plus",
            "countries": [
                74,
                230
            ]
        }
    },
    {
        "model": "api.service",
        "pk": 62,
        "fields": {
            "name": "Dota 2",
            "cname": "DOTA2",
            "path": "/statut/dota2",
            "countries": [
                74,
                230
            ]
        }
    },
    {
        "model": "api.service",
        "pk": 63,
        "fields": {
            "name": "Dropbox",
            "cname": "DROPBOX",
            "path": "/statut/dropbox",
            "countries": [
                74,
                230
            ]
        }
    },
    {
        "model": "api.service",
        "pk": 64,
        "fields": {
            "name": "Duke Energy",
            "cname": "DUKEENERGY",
            "path": "/statut/duke-energy",
            "countries": [
                230
            ]
        }
    },
    {
        "model": "api.service",
        "pk": 65,
        "fields": {
            "name": "Electronic Arts",
            "cname": "EA",
            "path": "/statut/ea-games-electronic-arts",
            "countries": [
                74,
                230
            ]
        }
    },
    {
        "model": "api.service",
        "pk": 66,
        "fields": {
            "name": "Earthlink",
            "cname": "EARTHLINK",
            "path": "/statut/earthlinl",
            "countries": [
                230
            ]
        }
    },
    {
        "model": "api.service",
        "pk": 67,
        "fields": {
            "name": "Ebay",
            "cname": "EBAY",
            "path": "/statut/ebay",
            "countries": [
                74,
                230
            ]
        }
    },
    {
        "model": "api.service",
        "pk": 68,
        "fields": {
            "name": "Entergy",
            "cname": "ENTERGY",
            "path": "/statut/entergy",
            "countries": [
                230
            ]
        }
    },
    {
        "model": "api.service",
        "pk": 69,
        "fields": {
            "name": "Etoro",
            "cname": "ETORO",
            "path": "/statut/etoro",
            "countries": [
                74,
                230
            ]
        }
    },
    {
        "model": "api.service",
        "pk": 70,
        "fields": {
            "name": "Etrade",
            "cname": "ETRADE",
            "path": "/statut/etrade",
            "countries": [
                74,
                230
            ]
        }
    },
    {
        "model": "api.service",
        "pk": 71,
        "fields": {
            "name": "Eversource Energy",
            "cname": "EVERSOURCEENERGY",
            "path": "/statut/eversource-energy",
            "countries": [
                230
            ]
        }
    },
    {
        "model": "api.service",
        "pk": 72,
        "fields": {
            "name": "Facebook",
            "cname": "FACEBOOK",
            "path": "/statut/facebook",
            "countries": [
                74,
                230
            ]
        }
    },
    {
        "model": "api.service",
        "pk": 73,
        "fields": {
            "name": "Facebook Gaming",
            "cname": "FACEBOOKGAMING",
            "path": "/statut/facebook-gaming",
            "countries": [
                230
            ]
        }
    },
    {
        "model": "api.service",
        "pk": 74,
        "fields": {
            "name": "Facebook Messenger",
            "cname": "MESSENGER",
            "path": "/statut/facebook-messenger",
            "countries": [
                74,
                230
            ]
        }
    },
    {
        "model": "api.service",
        "pk": 75,
        "fields": {
            "name": "Fall Guys",
            "cname": "FALLGUYS",
            "path": "/statut/fallguys",
            "countries": [
                74,
                230
            ]
        }
    },
    {
        "model": "api.service",
        "pk": 76,
        "fields": {
            "name": "Fallout 76",
            "cname": "FALLOUT76",
            "path": "/statut/fallout-76",
            "countries": [
                74,
                230
            ]
        }
    },
    {
        "model": "api.service",
        "pk": 77,
        "fields": {
            "name": "Farmers Insurance",
            "cname": "FARMERSINSURANCE",
            "path": "/statut/farmers-insurance",
            "countries": [
                230
            ]
        }
    },
    {
        "model": "api.service",
        "pk": 78,
        "fields": {
            "name": "Fedex",
            "cname": "FEDEX",
            "path": "/statut/fedex",
            "countries": [
                74,
                230
            ]
        }
    },
    {
        "model": "api.service",
        "pk": 79,
        "fields": {
            "name": "FIFA",
            "cname": "FIFA",
            "path": "/statut/fifa-ea-sports",
            "countries": [
                74,
                230
            ]
        }
    },
    {
        "model": "api.service",
        "pk": 80,
        "fields": {
            "name": "Fibit",
            "cname": "FIBIT",
            "path": "/statut/fibit",
            "countries": [
                74,
                230
            ]
        }
    },
    {
        "model": "api.service",
        "pk": 81,
        "fields": {
            "name": "Forida Power and Light",
            "cname": "FLORIDAPOWERANDLIGHT",
            "path": "/statut/florida-power-and-light",
            "countries": [
                230
            ]
        }
    },
    {
        "model": "api.service",
        "pk": 82,
        "fields": {
            "name": "For Honor",
            "cname": "FORHONOR",
            "path": "/statut/for-honor",
            "countries": [
                74,
                230
            ]
        }
    },
    {
        "model": "api.service",
        "pk": 83,
        "fields": {
            "name": "Forex.com",
            "cname": "FOREXDOTCOM",
            "path": "/statut/forex-dot-com",
            "countries": [
                74,
                230
            ]
        }
    },
    {
        "model": "api.service",
        "pk": 84,
        "fields": {
            "name": "Fornite",
            "cname": "FORNITE",
            "path": "/statut/fornite",
            "countries": [
                74,
                230
            ]
        }
    },
    {
        "model": "api.service",
        "pk": 85,
        "fields": {
            "name": "Free",
            "cname": "FREE",
            "path": "/statut/free",
            "countries": [
                74
            ]
        }
    },
    {
        "model": "api.service",
        "pk": 86,
        "fields": {
            "name": "Friday The 13th: The Game",
            "cname": "FRIDAYTHE13TH",
            "path": "/statut/friday-the-13th-game",
            "countries": [
                74,
                230
            ]
        }
    },
    {
        "model": "api.service",
        "pk": 87,
        "fields": {
            "name": "Frontier",
            "cname": "FRONTIER",
            "path": "/statut/frontier",
            "countries": [
                230
            ]
        }
    },
    {
        "model": "api.service",
        "pk": 88,
        "fields": {
            "name": "Garmin Connect",
            "cname": "GARMIN",
            "path": "/statut/garmin-connect",
            "countries": [
                74,
                230
            ]
        }
    },
    {
        "model": "api.service",
        "pk": 89,
        "fields": {
            "name": "Gci",
            "cname": "GCI",
            "path": "/statut/gci",
            "countries": [
                230
            ]
        }
    },
    {
        "model": "api.service",
        "pk": 90,
        "fields": {
            "name": "GDAX",
            "cname": "GDAX",
            "path": "/statut/gdax",
            "countries": [
                74,
                230
            ]
        }
    },
    {
        "model": "api.service",
        "pk": 91,
        "fields": {
            "name": "Gears of War",
            "cname": "GEARSOFXAR",
            "path": "/statut/gears-of-war",
            "countries": [
                74,
                230
            ]
        }
    },
    {
        "model": "api.service",
        "pk": 92,
        "fields": {
            "name": "Geico",
            "cname": "GEICO",
            "path": "/statut/geico",
            "countries": [
                230
            ]
        }
    },
    {
        "model": "api.service",
        "pk": 93,
        "fields": {
            "name": "Georgia Power",
            "cname": "GEORGIAPOWER",
            "path": "/statut/georgia-power",
            "countries": [
                230
            ]
        }
    },
    {
        "model": "api.service",
        "pk": 94,
        "fields": {
            "name": "GitHub",
            "cname": "GITHUB",
            "path": "/statut/github",
            "countries": [
                74,
                230
            ]
        }
    },
    {
        "model": "api.service",
        "pk": 95,
        "fields": {
            "name": "Gmail",
            "cname": "GMAIL",
            "path": "/statut/gmail",
            "countries": [
                74,
                230
            ]
        }
    },
    {
        "model": "api.service",
        "pk": 96,
        "fields": {
            "name": "GoDaddy",
            "cname": "GODADDY",
            "path": "/statut/godaddy",
            "countries": [
                74,
                230
            ]
        }
    },
    {
        "model": "api.service",
        "pk": 97,
        "fields": {
            "name": "Google Cloud Platform",
            "cname": "GOOGLECLOUD",
            "path": "/statut/google-cloud",
            "countries": [
                74,
                230
            ]
        }
    },
    {
        "model": "api.service",
        "pk": 98,
        "fields": {
            "name": "Google Fi",
            "cname": "GOOGLEFI",
            "path": "/statut/google-fi",
            "countries": [
                230
            ]
        }
    },
    {
        "model": "api.service",
        "pk": 99,
        "fields": {
            "name": "Google Fiber",
            "cname": "GOOGLEFIBER",
            "path": "/statut/google-fiber",
            "countries": [
                230
            ]
        }
    },
    {
        "model": "api.service",
        "pk": 100,
        "fields": {
            "name": "Google Nest",
            "cname": "GOOGLENEST",
            "path": "/statut/google-nest",
            "countries": [
                74,
                230
            ]
        }
    },
    {
        "model": "api.service",
        "pk": 101,
        "fields": {
            "name": "Grande Communications",
            "cname": "GRANDECOMMUNICATIONS",
            "path": "/statut/grande-communications",
            "countries": [
                230
            ]
        }
    },
    {
        "model": "api.service",
        "pk": 102,
        "fields": {
            "name": "Grayson Collin Electric Cooperative",
            "cname": "GCEC",
            "path": "/statut/grayson-collin-electric-cooperative-gcec",
            "countries": [
                230
            ]
        }
    },
    {
        "model": "api.service",
        "pk": 103,
        "fields": {
            "name": "Greenlight Networks",
            "cname": "GREENLIGHTNETWORK",
            "path": "/statut/greenlight-network",
            "countries": [
                230
            ]
        }
    },
    {
        "model": "api.service",
        "pk": 104,
        "fields": {
            "name": "Grand theft auto V",
            "cname": "GTAV",
            "path": "/statut/gta-v-grand-theft-auto-v",
            "countries": [
                74,
                230
            ]
        }
    },
    {
        "model": "api.service",
        "pk": 105,
        "fields": {
            "name": "H1Z1",
            "cname": "H1Z1",
            "path": "/statut/h1z1",
            "countries": [
                74,
                230
            ]
        }
    },
    {
        "model": "api.service",
        "pk": 106,
        "fields": {
            "name": "Halo",
            "cname": "HALO",
            "path": "/statut/halo-game",
            "countries": [
                74,
                230
            ]
        }
    },
    {
        "model": "api.service",
        "pk": 107,
        "fields": {
            "name": "Hawaiian Telcom",
            "cname": "HAWAIIANTELCOM",
            "path": "/statut/hawaiian-telcom",
            "countries": [
                230
            ]
        }
    },
    {
        "model": "api.service",
        "pk": 108,
        "fields": {
            "name": "HBO Go",
            "cname": "HBOGO",
            "path": "/statut/hbo-go",
            "countries": [
                230
            ]
        }
    },
    {
        "model": "api.service",
        "pk": 109,
        "fields": {
            "name": "HBO Max",
            "cname": "HBOMAX",
            "path": "/statut/hbo-max",
            "countries": [
                74,
                230
            ]
        }
    },
    {
        "model": "api.service",
        "pk": 110,
        "fields": {
            "name": "HostGator",
            "cname": "HOSTGATOR",
            "path": "/statut/hostgator",
            "countries": [
                74,
                230
            ]
        }
    },
    {
        "model": "api.service",
        "pk": 111,
        "fields": {
            "name": "Hughesnet USA",
            "cname": "HUGHESNETUSA",
            "path": "/statut/hughesnet-usa",
            "countries": [
                230
            ]
        }
    },
    {
        "model": "api.service",
        "pk": 112,
        "fields": {
            "name": "Hulu",
            "cname": "HULU",
            "path": "/statut/hulu",
            "countries": [
                74,
                230
            ]
        }
    },
    {
        "model": "api.service",
        "pk": 113,
        "fields": {
            "name": "IG",
            "cname": "IGBROKER",
            "path": "/statut/ig-broker",
            "countries": [
                74,
                230
            ]
        }
    },
    {
        "model": "api.service",
        "pk": 114,
        "fields": {
            "name": "Indiana Michigan Power",
            "cname": "INDIANAMICHIGANPOWER",
            "path": "/statut/indiana-michigan-power",
            "countries": [
                230
            ]
        }
    },
    {
        "model": "api.service",
        "pk": 115,
        "fields": {
            "name": "Instagram",
            "cname": "INSTAGRAM",
            "path": "/statut/instagram",
            "countries": [
                74,
                230
            ]
        }
    },
    {
        "model": "api.service",
        "pk": 116,
        "fields": {
            "name": "Interactive Brokers",
            "cname": "INTERACTIVEBROKERS",
            "path": "/statut/interactive-brokers",
            "countries": [
                74,
                230
            ]
        }
    },
    {
        "model": "api.service",
        "pk": 117,
        "fields": {
            "name": "IRS USA",
            "cname": "IRSUSA",
            "path": "/statut/irs-usa",
            "countries": [
                230
            ]
        }
    },
    {
        "model": "api.service",
        "pk": 118,
        "fields": {
            "name": "iTunes",
            "cname": "ITUNES",
            "path": "/statut/itunes",
            "countries": [
                74,
                230
            ]
        }
    },
    {
        "model": "api.service",
        "pk": 119,
        "fields": {
            "name": "Kraken",
            "cname": "KRAKEN",
            "path": "/statut/kraken",
            "countries": [
                74,
                230
            ]
        }
    },
    {
        "model": "api.service",
        "pk": 120,
        "fields": {
            "name": "League Of Legends",
            "cname": "LEAGUEOFLEGENDS",
            "path": "/statut/league-of-legends",
            "countries": [
                74,
                230
            ]
        }
    },
    {
        "model": "api.service",
        "pk": 121,
        "fields": {
            "name": "Liberty Mutual",
            "cname": "LIBERTYMUTUAL",
            "path": "/statut/liberty-mutual",
            "countries": [
                230
            ]
        }
    },
    {
        "model": "api.service",
        "pk": 122,
        "fields": {
            "name": "London Capital Group",
            "cname": "LCG",
            "path": "/statut/london-capital-group-lgc",
            "countries": [
                74,
                230
            ]
        }
    },
    {
        "model": "api.service",
        "pk": 123,
        "fields": {
            "name": "Lumos Networks",
            "cname": "LUMOSNETWORKS",
            "path": "/statut/lumos-networks",
            "countries": [
                230
            ]
        }
    },
    {
        "model": "api.service",
        "pk": 124,
        "fields": {
            "name": "Mass Effect Andromeda",
            "cname": "MASEFFECT",
            "path": "/statut/mass-effect-andromeda",
            "countries": [
                74,
                230
            ]
        }
    },
    {
        "model": "api.service",
        "pk": 125,
        "fields": {
            "name": "Mediacom",
            "cname": "MEDIACOM",
            "path": "/statut/mediacom",
            "countries": [
                230
            ]
        }
    },
    {
        "model": "api.service",
        "pk": 126,
        "fields": {
            "name": "Metronet",
            "cname": "METRONET",
            "path": "/statut/metronet",
            "countries": [
                230
            ]
        }
    },
    {
        "model": "api.service",
        "pk": 127,
        "fields": {
            "name": "Metropcs",
            "cname": "METROPCS",
            "path": "/statut/metropcs",
            "countries": [
                230
            ]
        }
    },
    {
        "model": "api.service",
        "pk": 128,
        "fields": {
            "name": "Microsoft Azure",
            "cname": "AZURE",
            "path": "/statut/microsoft-azure",
            "countries": [
                74,
                230
            ]
        }
    },
    {
        "model": "api.service",
        "pk": 129,
        "fields": {
            "name": "Microsoft Teams",
            "cname": "TEAMS",
            "path": "/statut/microsoft-teams",
            "countries": [
                74,
                230
            ]
        }
    },
    {
        "model": "api.service",
        "pk": 130,
        "fields": {
            "name": "Midco",
            "cname": "MIDCO",
            "path": "/statut/midco",
            "countries": [
                74,
                230
            ]
        }
    },
    {
        "model": "api.service",
        "pk": 131,
        "fields": {
            "name": "Minecraft",
            "cname": "MINECRAFT",
            "path": "/statut/minecraft",
            "countries": [
                74,
                230
            ]
        }
    },
    {
        "model": "api.service",
        "pk": 132,
        "fields": {
            "name": "Monster Hunter",
            "cname": "MONSTERHUNTER",
            "path": "/statut/monster-hunter",
            "countries": [
                74,
                230
            ]
        }
    },
    {
        "model": "api.service",
        "pk": 133,
        "fields": {
            "name": "Namecheap",
            "cname": "NAMECHEAP",
            "path": "/statut/namecheap",
            "countries": [
                74,
                230
            ]
        }
    },
    {
        "model": "api.service",
        "pk": 134,
        "fields": {
            "name": "National Grid Us",
            "cname": "NATIONALGRIDUS",
            "path": "/statut/national-grid-us",
            "countries": [
                230
            ]
        }
    },
    {
        "model": "api.service",
        "pk": 135,
        "fields": {
            "name": "Nationwide",
            "cname": "NATIONWIDE",
            "path": "/statut/nationwide",
            "countries": [
                230
            ]
        }
    },
    {
        "model": "api.service",
        "pk": 136,
        "fields": {
            "name": "Netflix",
            "cname": "NETFLIX",
            "path": "/statut/netflix",
            "countries": [
                74,
                230
            ]
        }
    },
    {
        "model": "api.service",
        "pk": 137,
        "fields": {
            "name": "New World",
            "cname": "NEWWORLD",
            "path": "/statut/new-world-game",
            "countries": [
                74,
                230
            ]
        }
    },
    {
        "model": "api.service",
        "pk": 138,
        "fields": {
            "name": "Nintendo",
            "cname": "NINTENDO",
            "path": "/statut/nintendo-switch",
            "countries": [
                74,
                230
            ]
        }
    },
    {
        "model": "api.service",
        "pk": 139,
        "fields": {
            "name": "Northland Communications",
            "cname": "NORTHLANDCOMMUNICATIONS",
            "path": "/statut/northland-communications",
            "countries": [
                230
            ]
        }
    },
    {
        "model": "api.service",
        "pk": 140,
        "fields": {
            "name": "Numericable",
            "cname": "NUMERICABLE",
            "path": "/statut/numericable-france",
            "countries": [
                74
            ]
        }
    },
    {
        "model": "api.service",
        "pk": 141,
        "fields": {
            "name": "OANDA",
            "cname": "OANDA",
            "path": "/statut/oanda",
            "countries": [
                74,
                230
            ]
        }
    },
    {
        "model": "api.service",
        "pk": 142,
        "fields": {
            "name": "Office 365",
            "cname": "OFFICE365",
            "path": "/statut/office-365",
            "countries": [
                74,
                230
            ]
        }
    },
    {
        "model": "api.service",
        "pk": 143,
        "fields": {
            "name": "Oncor",
            "cname": "ONCOR",
            "path": "/statut/oncor",
            "countries": [
                230
            ]
        }
    },
    {
        "model": "api.service",
        "pk": 144,
        "fields": {
            "name": "Optical",
            "cname": "OPTICALTEL",
            "path": "/statut/opticaltel",
            "countries": [
                230
            ]
        }
    },
    {
        "model": "api.service",
        "pk": 145,
        "fields": {
            "name": "Optimum Cablevision",
            "cname": "OPTIMUMCABLEVISION",
            "path": "/statut/optimum-cablevision",
            "countries": [
                230
            ]
        }
    },
    {
        "model": "api.service",
        "pk": 146,
        "fields": {
            "name": "Orange",
            "cname": "ORANGE",
            "description": "French Internet provider",
            "path": "/statut/orange-france",
            "website": "www.orange.fr",
            "twitterUsername": "Get Service",
            "countries": [
                74
            ]
        }
    },
    {
        "model": "api.service",
        "pk": 147,
        "fields": {
            "name": "Orange Bank the besti <3",
            "cname": "ORANGEBANK",
            "path": "/statut/orange-bank",
            "countries": [
                74
            ]
        }
    },
    {
        "model": "api.service",
        "pk": 148,
        "fields": {
            "name": "Origin EA",
            "cname": "ORIGINEA",
            "path": "/statut/origin-ea",
            "countries": [
                74,
                230
            ]
        }
    },
    {
        "model": "api.service",
        "pk": 149,
        "fields": {
            "name": "Outlook",
            "cname": "OUTLOOK",
            "path": "/statut/outlook-hotmail",
            "countries": [
                74,
                230
            ]
        }
    },
    {
        "model": "api.service",
        "pk": 150,
        "fields": {
            "name": "Overwatch",
            "cname": "OVERWATCHGAMES",
            "path": "/statut/overwatch-game",
            "countries": [
                74,
                230
            ]
        }
    },
    {
        "model": "api.service",
        "pk": 151,
        "fields": {
            "name": "Paladins",
            "cname": "PALADINS",
            "path": "/statut/paladins",
            "countries": [
                74,
                230
            ]
        }
    },
    {
        "model": "api.service",
        "pk": 152,
        "fields": {
            "name": "Pandora",
            "cname": "PANDORA",
            "path": "/statut/pandora",
            "countries": [
                230
            ]
        }
    },
    {
        "model": "api.service",
        "pk": 153,
        "fields": {
            "name": "Paramount Plus",
            "cname": "PARAMOUNTPLUS",
            "path": "/statut/paramount-plus",
            "countries": [
                74,
                230
            ]
        }
    },
    {
        "model": "api.service",
        "pk": 154,
        "fields": {
            "name": "Path Of Exile",
            "cname": "PATHOFEXILE",
            "path": "/statut/path-of-exile",
            "countries": [
                74,
                230
            ]
        }
    },
    {
        "model": "api.service",
        "pk": 155,
        "fields": {
            "name": "PayPal",
            "cname": "PAYPAL",
            "path": "/statut/paypal",
            "countries": [
                74,
                230
            ]
        }
    },
    {
        "model": "api.service",
        "pk": 156,
        "fields": {
            "name": "Peackock TV",
            "cname": "PEACKOCKTV",
            "path": "/statut/peackock-tv",
            "countries": [
                74,
                230
            ]
        }
    },
    {
        "model": "api.service",
        "pk": 157,
        "fields": {
            "name": "Peco Energy",
            "cname": "PECOENERGY",
            "path": "/statut/peco-energy",
            "countries": [
                230
            ]
        }
    },
    {
        "model": "api.service",
        "pk": 158,
        "fields": {
            "name": "Pepperstone",
            "cname": "PEPPERSTONE",
            "path": "/statut/pepperstone",
            "countries": [
                74,
                230
            ]
        }
    },
    {
        "model": "api.service",
        "pk": 159,
        "fields": {
            "name": "Pg And E",
            "cname": "PGANDE",
            "path": "/statut/pg-and-e",
            "countries": [
                230
            ]
        }
    },
    {
        "model": "api.service",
        "pk": 160,
        "fields": {
            "name": "Player Unknowns Battleground",
            "cname": "PUBG",
            "path": "/statut/playerunknowns-battlegrounds",
            "countries": [
                74,
                230
            ]
        }
    },
    {
        "model": "api.service",
        "pk": 161,
        "fields": {
            "name": "PlayStation Network",
            "cname": "PSN",
            "path": "/statut/playstation-network-psn",
            "countries": [
                74,
                230
            ]
        }
    },
    {
        "model": "api.service",
        "pk": 162,
        "fields": {
            "name": "Plus500",
            "cname": "PLUS500",
            "path": "/statut/plus500",
            "countries": [
                74,
                230
            ]
        }
    },
    {
        "model": "api.service",
        "pk": 163,
        "fields": {
            "name": "Pok\u00e9mon GO",
            "cname": "POKEMONGO",
            "path": "/statut/pokemon-go",
            "countries": [
                74,
                230
            ]
        }
    },
    {
        "model": "api.service",
        "pk": 164,
        "fields": {
            "name": "Progressive",
            "cname": "PROGRESSIVE",
            "path": "/statut/progressive",
            "countries": [
                230
            ]
        }
    },
    {
        "model": "api.service",
        "pk": 165,
        "fields": {
            "name": "RCN",
            "cname": "RCN",
            "path": "/statut/rcn",
            "countries": [
                230
            ]
        }
    },
    {
        "model": "api.service",
        "pk": 166,
        "fields": {
            "name": "Reddit",
            "cname": "REDDIT",
            "path": "/statut/reddit",
            "countries": [
                74,
                230
            ]
        }
    },
    {
        "model": "api.service",
        "pk": 167,
        "fields": {
            "name": "Ring",
            "cname": "RING",
            "path": "/statut/ring",
            "countries": [
                74,
                230
            ]
        }
    },
    {
        "model": "api.service",
        "pk": 168,
        "fields": {
            "name": "Rise Broadband",
            "cname": "RISEBROADBAND",
            "path": "/statut/rise-broadband",
            "countries": [
                230
            ]
        }
    },
    {
        "model": "api.service",
        "pk": 169,
        "fields": {
            "name": "RobinHood",
            "cname": "ROBINHOOD",
            "path": "/statut/robinhood",
            "countries": [
                74,
                230
            ]
        }
    },
    {
        "model": "api.service",
        "pk": 170,
        "fields": {
            "name": "Roblox",
            "cname": "ROBLOX",
            "path": "/statut/roblox",
            "countries": [
                74,
                230
            ]
        }
    },
    {
        "model": "api.service",
        "pk": 171,
        "fields": {
            "name": "Rocket League",
            "cname": "ROCKETLEAGUE",
            "path": "/statut/rocket-league",
            "countries": [
                74,
                230
            ]
        }
    },
    {
        "model": "api.service",
        "pk": 172,
        "fields": {
            "name": "Roku",
            "cname": "ROKU",
            "path": "/statut/roku",
            "countries": [
                74,
                230
            ]
        }
    },
    {
        "model": "api.service",
        "pk": 173,
        "fields": {
            "name": "Runescape",
            "cname": "RUNESCAPE",
            "path": "/statut/runescape",
            "countries": [
                74,
                230
            ]
        }
    },
    {
        "model": "api.service",
        "pk": 174,
        "fields": {
            "name": "Southern California Edison",
            "cname": "SCE",
            "path": "/statut/sce-southern-california-edison",
            "countries": [
                230
            ]
        }
    },
    {
        "model": "api.service",
        "pk": 175,
        "fields": {
            "name": "Sea Of Thieves",
            "cname": "SEAOFTHIEVES",
            "path": "/statut/sea-of-thieves-game",
            "countries": [
                74,
                230
            ]
        }
    },
    {
        "model": "api.service",
        "pk": 176,
        "fields": {
            "name": "Service Electric",
            "cname": "SERVICEELECTRIC",
            "path": "/statut/service-electric",
            "countries": [
                230
            ]
        }
    },
    {
        "model": "api.service",
        "pk": 177,
        "fields": {
            "name": "SFR",
            "cname": "SFR",
            "path": "/statut/sfr",
            "countries": [
                74
            ]
        }
    },
    {
        "model": "api.service",
        "pk": 178,
        "fields": {
            "name": "Shazam",
            "cname": "SHAZAM",
            "path": "/statut/shazam",
            "countries": [
                74,
                230
            ]
        }
    },
    {
        "model": "api.service",
        "pk": 179,
        "fields": {
            "name": "Shentel",
            "cname": "SHENTEL",
            "path": "/statut/shentel",
            "countries": [
                230
            ]
        }
    },
    {
        "model": "api.service",
        "pk": 180,
        "fields": {
            "name": "Signal Messenger",
            "cname": "SIGNALMESSENGER",
            "path": "/statut/signal-messenger",
            "countries": [
                74,
                230
            ]
        }
    },
    {
        "model": "api.service",
        "pk": 181,
        "fields": {
            "name": "Simple Mobile",
            "cname": "SIMPLEMOBILE",
            "path": "/statut/simple-mobile",
            "countries": [
                230
            ]
        }
    },
    {
        "model": "api.service",
        "pk": 182,
        "fields": {
            "name": "Skype",
            "cname": "SKYPE",
            "path": "/statut/skype",
            "countries": [
                74,
                230
            ]
        }
    },
    {
        "model": "api.service",
        "pk": 183,
        "fields": {
            "name": "Slack",
            "cname": "SLACK",
            "path": "/statut/slack",
            "countries": [
                74,
                230
            ]
        }
    },
    {
        "model": "api.service",
        "pk": 184,
        "fields": {
            "name": "Slemco",
            "cname": "SLEMCO",
            "path": "/statut/slemco",
            "countries": [
                230
            ]
        }
    },
    {
        "model": "api.service",
        "pk": 185,
        "fields": {
            "name": "Sling",
            "cname": "SLING",
            "path": "/statut/sling",
            "countries": [
                230
            ]
        }
    },
    {
        "model": "api.service",
        "pk": 186,
        "fields": {
            "name": "Smite",
            "cname": "SMITE",
            "path": "/statut/smite",
            "countries": [
                74,
                230
            ]
        }
    },
    {
        "model": "api.service",
        "pk": 187,
        "fields": {
            "name": "Snapchat",
            "cname": "SNAPCHAT",
            "path": "/statut/snapchat",
            "countries": [
                74,
                230
            ]
        }
    },
    {
        "model": "api.service",
        "pk": 188,
        "fields": {
            "name": "Southwestern Electric Power SWEPCO",
            "cname": "SWEPCO",
            "path": "/statut/southwestern-electric-power-swepco",
            "countries": [
                230
            ]
        }
    },
    {
        "model": "api.service",
        "pk": 189,
        "fields": {
            "name": "Spotify",
            "cname": "SPOTIFY",
            "path": "/statut/spotify",
            "countries": [
                74,
                230
            ]
        }
    },
    {
        "model": "api.service",
        "pk": 190,
        "fields": {
            "name": "Star Wars Battlefront",
            "cname": "STARWARSBATTLEFRONT",
            "path": "/statut/star-wars-battlefront",
            "countries": [
                74,
                230
            ]
        }
    },
    {
        "model": "api.service",
        "pk": 191,
        "fields": {
            "name": "Starlink",
            "cname": "STARLINK",
            "path": "/statut/starlink",
            "countries": [
                74,
                230
            ]
        }
    },
    {
        "model": "api.service",
        "pk": 192,
        "fields": {
            "name": "State Farm",
            "cname": "STATEFARM",
            "path": "/statut/state-farm",
            "countries": [
                230
            ]
        }
    },
    {
        "model": "api.service",
        "pk": 193,
        "fields": {
            "name": "Steam",
            "cname": "STEAM",
            "path": "/statut/steam",
            "countries": [
                74,
                230
            ]
        }
    },
    {
        "model": "api.service",
        "pk": 194,
        "fields": {
            "name": "Straight Talk",
            "cname": "STRAIGHTTALK",
            "path": "/statut/straight-talk",
            "countries": [
                230
            ]
        }
    },
    {
        "model": "api.service",
        "pk": 195,
        "fields": {
            "name": "Suddenlink",
            "cname": "SUDDENKINK",
            "path": "/statut/suddenlink",
            "countries": [
                230
            ]
        }
    },
    {
        "model": "api.service",
        "pk": 196,
        "fields": {
            "name": "Super Mario Run",
            "cname": "SUPERMARIORUN",
            "path": "/statut/super-mario-run",
            "countries": [
                74,
                230
            ]
        }
    },
    {
        "model": "api.service",
        "pk": 197,
        "fields": {
            "name": "T Mobile",
            "cname": "TMOBILE",
            "path": "/statut/t-mobile",
            "countries": [
                230
            ]
        }
    },
    {
        "model": "api.service",
        "pk": 198,
        "fields": {
            "name": "TD Ameritrade",
            "cname": "TDAMERITRADE",
            "path": "/statut/td-ameritrade",
            "countries": [
                74,
                230
            ]
        }
    },
    {
        "model": "api.service",
        "pk": 199,
        "fields": {
            "name": "TDS Telecom",
            "cname": "TDSTELECOM",
            "path": "/statut/tds-telecom",
            "countries": [
                230
            ]
        }
    },
    {
        "model": "api.service",
        "pk": 200,
        "fields": {
            "name": "Telegram",
            "cname": "TELEGRAM",
            "path": "/statut/telegram",
            "countries": [
                74,
                230
            ]
        }
    },
    {
        "model": "api.service",
        "pk": 201,
        "fields": {
            "name": "The Elder Scrolls Online",
            "cname": "THEELDERSCROLLSONLINE",
            "path": "/statut/the-elder-scrolls-online",
            "countries": [
                74,
                230
            ]
        }
    },
    {
        "model": "api.service",
        "pk": 202,
        "fields": {
            "name": "TikTok",
            "cname": "TIKTOK",
            "path": "/statut/tiktok",
            "countries": [
                74,
                230
            ]
        }
    },
    {
        "model": "api.service",
        "pk": 203,
        "fields": {
            "name": "Tinder",
            "cname": "TINDER",
            "path": "/statut/tinder",
            "countries": [
                74,
                230
            ]
        }
    },
    {
        "model": "api.service",
        "pk": 204,
        "fields": {
            "name": "Tom Clancy: Ghost Recon",
            "cname": "GHOSTRECON",
            "path": "/statut/tom-clancy-ghost-recon",
            "countries": [
                74,
                230
            ]
        }
    },
    {
        "model": "api.service",
        "pk": 205,
        "fields": {
            "name": "Tom Clancy: Rainbow Six Siege",
            "cname": "RAINBOWSIXSIEGE",
            "path": "/statut/tom-clancy-rainbow-six-siege",
            "countries": [
                74,
                230
            ]
        }
    },
    {
        "model": "api.service",
        "pk": 206,
        "fields": {
            "name": "Tom Clancy: The Division",
            "cname": "THEDIVISION",
            "path": "/statut/tom-clancys-the-division",
            "countries": [
                74,
                230
            ]
        }
    },
    {
        "model": "api.service",
        "pk": 207,
        "fields": {
            "name": "Tracfone Wirless",
            "cname": "TRACFONWIRLESS",
            "path": "/statut/tracfone-wirless",
            "countries": [
                230
            ]
        }
    },
    {
        "model": "api.service",
        "pk": 208,
        "fields": {
            "name": "Trading 212",
            "cname": "TRADING212",
            "path": "/statut/trading-212",
            "countries": [
                74,
                230
            ]
        }
    },
    {
        "model": "api.service",
        "pk": 209,
        "fields": {
            "name": "Twitch",
            "cname": "TWITCH",
            "path": "/statut/twitch",
            "countries": [
                74,
                230
            ]
        }
    },
    {
        "model": "api.service",
        "pk": 210,
        "fields": {
            "name": "Twitter",
            "cname": "TWITTER",
            "path": "/statut/twitter",
            "countries": [
                74,
                230
            ]
        }
    },
    {
        "model": "api.service",
        "pk": 211,
        "fields": {
            "name": "Uplay",
            "cname": "UPLAY",
            "path": "/statut/uplay-ubisoft",
            "countries": [
                74,
                230
            ]
        }
    },
    {
        "model": "api.service",
        "pk": 212,
        "fields": {
            "name": "UPS",
            "cname": "UPS",
            "path": "/statut/ups",
            "countries": [
                74,
                230
            ]
        }
    },
    {
        "model": "api.service",
        "pk": 213,
        "fields": {
            "name": "US Cellular",
            "cname": "USCELLULAR",
            "path": "/statut/us-cellular",
            "countries": [
                230
            ]
        }
    },
    {
        "model": "api.service",
        "pk": 214,
        "fields": {
            "name": "United Services Automobile Association",
            "cname": "USAA",
            "path": "/statut/usaa",
            "countries": [
                230
            ]
        }
    },
    {
        "model": "api.service",
        "pk": 215,
        "fields": {
            "name": "United States Postal Service",
            "cname": "USPS",
            "path": "/statut/usps",
            "countries": [
                230
            ]
        }
    },
    {
        "model": "api.service",
        "pk": 216,
        "fields": {
            "name": "Valorant",
            "cname": "VALORANT",
            "path": "/statut/valorant",
            "countries": [
                74,
                230
            ]
        }
    },
    {
        "model": "api.service",
        "pk": 217,
        "fields": {
            "name": "Vast Broadband",
            "cname": "VASTBROADBAND",
            "path": "/statut/vast-broadband",
            "countries": [
                230
            ]
        }
    },
    {
        "model": "api.service",
        "pk": 218,
        "fields": {
            "name": "Verizon",
            "cname": "VERIZON",
            "path": "/statut/verizon",
            "countries": [
                230
            ]
        }
    },
    {
        "model": "api.service",
        "pk": 219,
        "fields": {
            "name": "Verizon FIOS",
            "cname": "VERIZONFIOS",
            "path": "/statut/verizon-fios",
            "countries": [
                230
            ]
        }
    },
    {
        "model": "api.service",
        "pk": 220,
        "fields": {
            "name": "Viasat",
            "cname": "VIASAT",
            "path": "/statut/viasat",
            "countries": [
                230
            ]
        }
    },
    {
        "model": "api.service",
        "pk": 221,
        "fields": {
            "name": "Viber",
            "cname": "VIBER",
            "path": "/statut/viber",
            "countries": [
                74,
                230
            ]
        }
    },
    {
        "model": "api.service",
        "pk": 222,
        "fields": {
            "name": "Virgin Mobile",
            "cname": "VIRGINMOBILE",
            "path": "/statut/virgin-mobile",
            "countries": [
                74,
                230
            ]
        }
    },
    {
        "model": "api.service",
        "pk": 223,
        "fields": {
            "name": "Walmart Family Mobile",
            "cname": "WALMARTFAMILYMOBILE",
            "path": "/statut/walmart-family-mobile",
            "countries": [
                230
            ]
        }
    },
    {
        "model": "api.service",
        "pk": 224,
        "fields": {
            "name": "Warframe",
            "cname": "WARFRAME",
            "path": "/statut/warframe",
            "countries": [
                74,
                230
            ]
        }
    },
    {
        "model": "api.service",
        "pk": 225,
        "fields": {
            "name": "Wave Broadband",
            "cname": "WAVEBROADBAND",
            "path": "/statut/wawe-broadband",
            "countries": [
                230
            ]
        }
    },
    {
        "model": "api.service",
        "pk": 226,
        "fields": {
            "name": "Waze",
            "cname": "WAZE",
            "path": "/statut/waze",
            "countries": [
                74,
                230
            ]
        }
    },
    {
        "model": "api.service",
        "pk": 227,
        "fields": {
            "name": "Wells Fargo",
            "cname": "WELLSFARGO",
            "path": "/statut/wells-fargo",
            "countries": [
                230
            ]
        }
    },
    {
        "model": "api.service",
        "pk": 228,
        "fields": {
            "name": "What's App",
            "cname": "WHATSAPP",
            "path": "/statut/whatsapp-messenger",
            "countries": [
                74,
                230
            ]
        }
    },
    {
        "model": "api.service",
        "pk": 229,
        "fields": {
            "name": "Wideopenwest Networks",
            "cname": "WIDEOPENWESTNETWORKS",
            "path": "/statut/wideopenwest-networks",
            "countries": [
                230
            ]
        }
    },
    {
        "model": "api.service",
        "pk": 230,
        "fields": {
            "name": "WINDSTREAM",
            "cname": "WINDSTREAM",
            "path": "/statut/windstream",
            "countries": [
                230
            ]
        }
    },
    {
        "model": "api.service",
        "pk": 231,
        "fields": {
            "name": "World Of Warcraft",
            "cname": "WORLDOFWARCRAFT",
            "path": "/statut/world-of-warcraft",
            "countries": [
                74,
                230
            ]
        }
    },
    {
        "model": "api.service",
        "pk": 232,
        "fields": {
            "name": "XBOX Live",
            "cname": "XBOXLIVE",
            "path": "/statut/xbox-live",
            "countries": [
                74,
                230
            ]
        }
    },
    {
        "model": "api.service",
        "pk": 233,
        "fields": {
            "name": "XM Trading",
            "cname": "XMTRADING",
            "path": "/statut/xm-trading",
            "countries": [
                74,
                230
            ]
        }
    },
    {
        "model": "api.service",
        "pk": 234,
        "fields": {
            "name": "XTB Trading",
            "cname": "XTBTRADING",
            "path": "/statut/xtb-trading",
            "countries": [
                74,
                230
            ]
        }
    },
    {
        "model": "api.service",
        "pk": 235,
        "fields": {
            "name": "Yahoo Mail",
            "cname": "YAHOOMAIL",
            "path": "/statut/yahoo-mail",
            "countries": [
                74,
                230
            ]
        }
    },
    {
        "model": "api.service",
        "pk": 236,
        "fields": {
            "name": "YouTube",
            "cname": "YOUTUBE",
            "path": "/statut/youtube",
            "countries": [
                74,
                230
            ]
        }
    },
    {
        "model": "api.service",
        "pk": 237,
        "fields": {
            "name": "Ziply Fiber",
            "cname": "ZIPLYFIBER",
            "path": "/statut/ziply-fiber",
            "countries": [
                230
            ]
        }
    },
    {
        "model": "api.service",
        "pk": 238,
        "fields": {
            "name": "Zoom",
            "cname": "ZOOM",
            "path": "/statut/zoom",
            "countries": [
                74
            ]
        }
    }
]
